submission/utils/__init__.py
submission/utils/app_enums.py
submission/utils/attachment.py
submission/utils/commonutils.py
submission/utils/cosutils.py
submission/utils/db2utils.py
submission/utils/watson_nlu_utils.py
submission/utils/watsondiscoveryutils.py
arunwagle_submission_intake_utils-1.0.8.dist-info/METADATA
arunwagle_submission_intake_utils-1.0.8.dist-info/WHEEL
arunwagle_submission_intake_utils-1.0.8.dist-info/top_level.txt
arunwagle_submission_intake_utils-1.0.8.dist-info/RECORD
