Metadata-Version: 2.1
Name: arunwagle-submission-intake-utils
Version: 1.0.8
Summary: Utils Package
Home-page: UNKNOWN
Author: Arun Wagle
Author-email: arun.wagle@ibm.com
License: UNKNOWN
Platform: UNKNOWN
Requires-Python: >=3.6
